sandbox_sdk/__init__.py
sandbox_sdk/_base_client.py
sandbox_sdk/_client.py
sandbox_sdk/_compat.py
sandbox_sdk/_constants.py
sandbox_sdk/_exceptions.py
sandbox_sdk/_files.py
sandbox_sdk/_models.py
sandbox_sdk/_qs.py
sandbox_sdk/_resource.py
sandbox_sdk/_response.py
sandbox_sdk/_streaming.py
sandbox_sdk/_types.py
sandbox_sdk/_version.py
sandbox_sdk/py.typed
sandbox_sdk/_utils/__init__.py
sandbox_sdk/_utils/_compat.py
sandbox_sdk/_utils/_datetime_parse.py
sandbox_sdk/_utils/_logs.py
sandbox_sdk/_utils/_proxy.py
sandbox_sdk/_utils/_reflection.py
sandbox_sdk/_utils/_resources_proxy.py
sandbox_sdk/_utils/_streams.py
sandbox_sdk/_utils/_sync.py
sandbox_sdk/_utils/_transform.py
sandbox_sdk/_utils/_typing.py
sandbox_sdk/_utils/_utils.py
sandbox_sdk/lib/.keep
sandbox_sdk/resources/__init__.py
sandbox_sdk/resources/sandboxes.py
sandbox_sdk/types/__init__.py
sandbox_sdk/types/pagination.py
sandbox_sdk/types/sandbox.py
sandbox_sdk/types/sandbox_create_params.py
sandbox_sdk/types/sandbox_create_response.py
sandbox_sdk/types/sandbox_delete_all_response.py
sandbox_sdk/types/sandbox_delete_params.py
sandbox_sdk/types/sandbox_delete_response.py
sandbox_sdk/types/sandbox_download_params.py
sandbox_sdk/types/sandbox_execute_params.py
sandbox_sdk/types/sandbox_execute_response.py
sandbox_sdk/types/sandbox_list_params.py
sandbox_sdk/types/sandbox_list_response.py
sandbox_sdk/types/sandbox_upload_params.py
sandbox_sdk/types/sandbox_upload_response.py
avm_sdk-1.2.0.dist-info/METADATA
avm_sdk-1.2.0.dist-info/WHEEL
avm_sdk-1.2.0.dist-info/licenses/LICENSE
avm_sdk-1.2.0.dist-info/RECORD
